spyder_pygmid/__init__.py
spyder_pygmid/spyder/__init__.py
spyder_pygmid/spyder/api.py
spyder_pygmid/spyder/plugin.py
spyder_pygmid/spyder/widgets/__init__.py
spyder_pygmid/spyder/widgets/confpage.py
spyder_pygmid/spyder/widgets/controller.py
spyder_pygmid/spyder/widgets/main_widget.py
spyder_pygmid-0.0.5.dist-info/AUTHORS.md
spyder_pygmid-0.0.5.dist-info/LICENSE.txt
spyder_pygmid-0.0.5.dist-info/METADATA
spyder_pygmid-0.0.5.dist-info/WHEEL
spyder_pygmid-0.0.5.dist-info/entry_points.txt
spyder_pygmid-0.0.5.dist-info/top_level.txt
spyder_pygmid-0.0.5.dist-info/RECORD
