Metadata-Version: 2.1
Name: spyder-pygmid
Version: 0.0.5
Summary: Use PyGMID sweep and lookup within spyder
Home-page: https://github.com/ollghra/pygmid-plugin
Author: Tiarnach Ó Riada
Author-email: tiarnach.oriada@tyndall.ie
License: Apache Software License 2.0
Classifier: Operating System :: MacOS
Classifier: Operating System :: Microsoft :: Windows
Classifier: Operating System :: POSIX :: Linux
Classifier: Programming Language :: Python :: 3
Classifier: Programming Language :: Python :: 3.7
Classifier: Programming Language :: Python :: 3.8
Classifier: Programming Language :: Python :: 3.9
Classifier: Development Status :: 5 - Production/Stable
Classifier: Intended Audience :: Education
Classifier: Intended Audience :: Science/Research
Classifier: Intended Audience :: Developers
Classifier: Topic :: Scientific/Engineering
Requires-Python: >= 3.7
License-File: LICENSE.txt
License-File: AUTHORS.md
Requires-Dist: pygmid
Requires-Dist: qtpy
Requires-Dist: qtawesome
Requires-Dist: spyder >=5.0.1
